hello_module/__init__.py
hello_module_228-0.0.0.dist-info/METADATA
hello_module_228-0.0.0.dist-info/WHEEL
hello_module_228-0.0.0.dist-info/top_level.txt
hello_module_228-0.0.0.dist-info/RECORD
