Metadata-Version: 2.1
Name: hello_module_228
Version: 0.0.0
Summary: dasdas
